2_2/Bilgisayar Organizasyonu/Ödevler/Ödev 1/Hazır/adder/half_adder.v
/* half adder module */

module half_adder(a,b,sum,carry);
    input a, b;
    output sum, carry;
    xor x1(sum, a, b);
    and a1(carry, a, b);
endmodule

2_2/Bilgisayar Organizasyonu/Ödevler/Ödev 1/Hazır/adder/full_adder.v
/* Full adder module */

`include "half_adder.v"

module full_adder(a, b, cin, sum, cout);
    input a, b, cin;
    output sum, cout;
    wire sum_half, carry_half, carry_half_2;

    half_adder ha1(a, b, sum_half, carry_half);
    half_adder ha2(sum_half, cin, sum, carry_half_2);
    or o1(cout, carry_half, carry_half_2);
endmodule

2_2/Bilgisayar Organizasyonu/Ödevler/Ödev 1/Hazır/adder/full_adder_tb.v
/* Test bench for full_adder.v */

`include "full_adder.v"

module full_adder_tb;
    reg a, b, cin;
    wire sum, cout;

    full_adder add1(a, b, cin, sum, cout);

    initial
        begin
            $dumpfile("full_adder.vcd");
            $dumpvars(0, full_adder_tb);
            a = 0; b = 0; cin = 0; #1
            a = 0; b = 0; cin = 1; #1
            a = 0; b = 1; cin = 0; #1
            a = 0; b = 1; cin = 1; #1
            a = 1; b = 0; cin = 0; #1
            a = 1; b = 0; cin = 1; #1
            a = 1; b = 1; cin = 0; #1
            a = 1; b = 1; cin = 1;
        end
endmodule

//iverilog -o full_adder_tb.vvp full_adder_tb.v
//vvp full_adder_tb.vvp

2_2/Bilgisayar Organizasyonu/Ödevler/Ödev 1/Hazır/adder/full_adder.vcd
$date
	Fri Mar 15 14:40:48 2024
$end
$version
	Icarus Verilog
$end
$timescale
	1s
$end
$scope module full_adder_tb $end
$var wire 1 ! sum $end
$var wire 1 " cout $end
$var reg 1 # a $end
$var reg 1 $ b $end
$var reg 1 % cin $end
$scope module add1 $end
$var wire 1 # a $end
$var wire 1 $ b $end
$var wire 1 % cin $end
$var wire 1 " cout $end
$var wire 1 & sum_half $end
$var wire 1 ! sum $end
$var wire 1 ' carry_half_2 $end
$var wire 1 ( carry_half $end
$scope module ha1 $end
$var wire 1 # a $end
$var wire 1 $ b $end
$var wire 1 ( carry $end
$var wire 1 & sum $end
$upscope $end
$scope module ha2 $end
$var wire 1 & a $end
$var wire 1 % b $end
$var wire 1 ' carry $end
$var wire 1 ! sum $end
$upscope $end
$upscope $end
$upscope $end
$enddefinitions $end
$comment Show the parameter values. $end
$dumpall
$end
#0
$dumpvars
0(
0'
0&
0%
0$
0#
0"
0!
$end
#1
1!
1%
#2
1&
0%
1$
#3
1"
0!
1'
1%
#4
0"
1!
0'
0%
0$
1#
#5
1"
0!
1'
1%
#6
0'
0&
1(
0%
1$
#7
1!
1%
