2_2/Bilgisayar Organizasyonu/Ödevler/Ödev 1/Hazır/mux/mux_2x1_1_st.v
module mux_2x1_1_st(out, a, b, select);
    input a, b, select;
    wire and_1, and_2, select_not;
    output out;
    not (select_not, select);
    and (and_1, a, select);
    and (and_2, b, select_not);
    or (out, and_1, and_2);
endmodule

2_2/Bilgisayar Organizasyonu/Ödevler/Ödev 1/Hazır/mux/mux_2x1_1_st_tb.v

`include "mux_2x1_1_st.v"

module mux_2x1_1_st_tb();

    reg a, b, select;

    wire out;
    
    mux_2x1_1_st UUT(
        .out(out),
        .a(a),
        .b(b),
        .select(select)
    );
    
    initial begin
        select = 0; a = 0; b = 0;
        #10 $display("select=%b a=%b b=%b out=%b", select, a, b, out);
        
        select = 1; a = 0; b = 0;
        #10 $display("select=%b a=%b b=%b out=%b", select, a, b, out);
        
        select = 0; a = 0; b = 1;
        #10 $display("select=%b a=%b b=%b out=%b", select, a, b, out);
        
        select = 1; a = 0; b = 1;
        #10 $display("select=%b a=%b b=%b out=%b", select, a, b, out);
        
        select = 0; a = 1; b = 0;
        #10 $display("select=%b a=%b b=%b out=%b", select, a, b, out);
        
        select = 1; a = 1; b = 0;
        #10 $display("select=%b a=%b b=%b out=%b", select, a, b, out);
        
        select = 0; a = 1; b = 1;
        #10 $display("select=%b a=%b b=%b out=%b", select, a, b, out);
        
        select = 1; a = 1; b = 1;
        #10 $display("select=%b a=%b b=%b out=%b", select, a, b, out);
        
        #10 $finish;
    end

initial begin
        $dumpfile("mux_2x1_1_st_tb.vcd");
        $dumpvars(0, mux_2x1_1_st_tb);
    end

endmodule

//iverilog -o mux_2x1_1_st_tb.vvp mux_2x1_1_st_tb.v
//vvp mux_2x1_1_st_tb.vvp

2_2/Bilgisayar Organizasyonu/Ödevler/Ödev 1/Hazır/mux/mux_2x1_1_st_tb.vcd
$date
	Fri Mar 15 14:48:58 2024
$end
$version
	Icarus Verilog
$end
$timescale
	1s
$end
$scope module mux_2x1_1_st_tb $end
$var wire 1 ! out $end
$var reg 1 " a $end
$var reg 1 # b $end
$var reg 1 $ select $end
$scope module UUT $end
$var wire 1 " a $end
$var wire 1 % and_1 $end
$var wire 1 & and_2 $end
$var wire 1 # b $end
$var wire 1 ! out $end
$var wire 1 $ select $end
$var wire 1 ' select_not $end
$upscope $end
$upscope $end
$enddefinitions $end
$comment Show the parameter values. $end
$dumpall
$end
#0
$dumpvars
1'
0&
0%
0$
0#
0"
0!
$end
#10
0'
1$
#20
1!
1&
1'
1#
0$
#30
0!
0&
0'
1$
#40
1'
0#
1"
0$
#50
1!
0'
1%
1$
#60
1&
1'
0%
1#
0$
#70
0&
0'
1%
1$
