2_2/Bilgisayar Organizasyonu/Ödevler/Ödev 1/Hazır/bcd_to_7_segment/bcd_to_7_segment.v
//Verilog module.
module bcd_to_7_segment(bcd,seg);
     
     //Declare inputs,outputs and internal variables.
     input [3:0] bcd;
     output [6:0] seg;
     reg [6:0] seg;

//always block for converting bcd digit into 7 segment format
    always @(bcd)
    begin
        case (bcd) //case statement
            0 : seg = 7'b1111110;
            1 : seg = 7'b0110000;
            2 : seg = 7'b1101101;
            3 : seg = 7'b1111001;
            4 : seg = 7'b0110011;
            5 : seg = 7'b1011011;
            6 : seg = 7'b1011111;
            7 : seg = 7'b1110000;
            8 : seg = 7'b1111111;
            9 : seg = 7'b1111011;
            //switch off 7 segment character when the bcd digit is not a decimal number.
            default : seg = 7'b0000000; 
        endcase
    end
    
endmodule

2_2/Bilgisayar Organizasyonu/Ödevler/Ödev 1/Hazır/bcd_to_7_segment/bcd_to_7_segment_tb.v
`include "bcd_to_7_segment.v"

module bcd_to_7_segment_tb;

    reg [3:0] bcd;
    wire [6:0] seg;
    integer i;

    bcd_to_7_segment uut (
        .bcd(bcd), 
        .seg(seg)
    );

    initial begin
        for(i = 0;i < 16;i = i+1) //run loop for 0 to 15.
        begin
            bcd = i; 
            #10;
        end     
    end
        
    initial begin
        $dumpfile("bcd_to_7_segment_tb.vcd");
        $dumpvars(0, bcd_to_7_segment_tb);
    end

endmodule

//iverilog -o bcd_to_7_segment_tb.vvp bcd_to_7_segment_tb.v
//vvp bcd_to_7_segment_tb.vvp     
//gtkwave

2_2/Bilgisayar Organizasyonu/Ödevler/Ödev 1/Hazır/bcd_to_7_segment/bcd_to_7_segment_tb.vcd
$date
	Thu Mar 14 14:40:52 2024
$end
$version
	Icarus Verilog
$end
$timescale
	1s
$end
$scope module bcd_to_7_segment_tb $end
$var wire 7 ! seg [6:0] $end
$var reg 4 " bcd [3:0] $end
$var integer 32 # i [31:0] $end
$scope module uut $end
$var wire 4 $ bcd [3:0] $end
$var reg 7 % seg [6:0] $end
$upscope $end
$upscope $end
$enddefinitions $end
$comment Show the parameter values. $end
$dumpall
$end
#0
$dumpvars
b1111110 %
b0 $
b0 #
b0 "
b1111110 !
$end
#10
b110000 !
b110000 %
b1 "
b1 $
b1 #
#20
b1101101 !
b1101101 %
b10 "
b10 $
b10 #
#30
b1111001 !
b1111001 %
b11 "
b11 $
b11 #
#40
b110011 !
b110011 %
b100 "
b100 $
b100 #
#50
b1011011 !
b1011011 %
b101 "
b101 $
b101 #
#60
b1011111 !
b1011111 %
b110 "
b110 $
b110 #
#70
b1110000 !
b1110000 %
b111 "
b111 $
b111 #
#80
b1111111 !
b1111111 %
b1000 "
b1000 $
b1000 #
#90
b1111011 !
b1111011 %
b1001 "
b1001 $
b1001 #
#100
b0 !
b0 %
b1010 "
b1010 $
b1010 #
#110
b1011 "
b1011 $
b1011 #
#120
b1100 "
b1100 $
b1100 #
#130
b1101 "
b1101 $
b1101 #
#140
b1110 "
b1110 $
b1110 #
#150
b1111 "
b1111 $
b1111 #
#160
b10000 #
