2_2/Bilgisayar Organizasyonu/Ödevler/Ödev 1/Hazır/counter/counter.v
//4-bit Binary Counter with Reset

module counter (
    input CLK, RESET, EN,
    output reg [3:0] Q,
    output reg CO
);

always @* begin
    CO = (Q == 4'b1111 && EN == 1'b1) ? 1'b1 : 1'b0;
end

always @(posedge CLK or posedge RESET) begin
    if (RESET) begin
        Q <= 4'b0000;
    end
    else if (EN) begin
        Q <= Q + 4'b0001;
    end
end

endmodule

2_2/Bilgisayar Organizasyonu/Ödevler/Ödev 1/Hazır/counter/counter_tb.v

`include "counter.v"
module counter_tb;

    
    // Inputs
    reg CLK, RESET, EN;
    
    // Outputs
    wire [3:0] Q;
    wire CO;

    counter uut (
        .CLK(CLK),
        .RESET(RESET),
        .EN(EN),
        .Q(Q),
        .CO(CO)
    );
    
    initial begin
        
        $dumpfile("counter_tb.vcd");
        $dumpvars(0, counter_tb);
        
        RESET = 1'b0;
        EN = 1'b1;
        CLK= 1'b0;
    
        #30; 
        
        // Reset
        RESET = 1'b1;
        #10; 
        RESET = 1'b0;
        #50; 
        
        RESET = 1'b0;
        EN = 1'b0; // Disable counter
    
        #30;
  
        $finish;
    end
    always #5 CLK=~CLK;
endmodule

// iverilog -o counter_tb.vvp counter_tb.v
// vvp counter_tb.vvp
// gtkwave

2_2/Bilgisayar Organizasyonu/Ödevler/Ödev 1/Hazır/counter/counter_tb.vcd
$date
	Fri Mar 15 13:14:55 2024
$end
$version
	Icarus Verilog
$end
$timescale
	1s
$end
$scope module counter_tb $end
$var wire 4 ! Q [3:0] $end
$var wire 1 " CO $end
$var reg 1 # CLK $end
$var reg 1 $ EN $end
$var reg 1 % RESET $end
$scope module uut $end
$var wire 1 # CLK $end
$var wire 1 $ EN $end
$var wire 1 % RESET $end
$var reg 1 " CO $end
$var reg 4 & Q [3:0] $end
$upscope $end
$upscope $end
$enddefinitions $end
$comment Show the parameter values. $end
$dumpall
$end
#0
$dumpvars
bx &
0%
1$
0#
x"
bx !
$end
#5
1#
#10
0#
#15
1#
#20
0#
#25
1#
#30
0"
b0 !
b0 &
0#
1%
#35
1#
#40
0#
0%
#45
b1 !
b1 &
1#
#50
0#
#55
b10 !
b10 &
1#
#60
0#
#65
b11 !
b11 &
1#
#70
0#
#75
b100 !
b100 &
1#
#80
0#
#85
b101 !
b101 &
1#
#90
0#
0$
