2_2/Bilgisayar Organizasyonu/Ödevler/Ödev 1/Hazır/bidirectional_counter/counter_fb.v
// 4-bit Binary Counter with Reset, Enable, and Direction control

module counter_fb (
    input CLK,     // Clock input
    input RESET,   // reset input
    input EN,      // Enable input
    input DIR,     // Direction (1 = up, 0 = down)
    output reg [3:0] Q,   // 4-bit output
    output reg CO         // Carry-out/overflow
);

//DIRECTION Carry
always @* begin
    if (DIR == 1'b1) // Count up
        CO = (Q == 4'b1111 && EN == 1'b1) ? 1'b1 : 1'b0;
    else // Count down
        CO = (Q == 4'b0000 && EN == 1'b1) ? 1'b1 : 1'b0;
end

always @(posedge CLK or posedge RESET) begin
    if (RESET) begin
        Q <= 4'b0000;
    end
    else if (EN) begin
        if (DIR == 1'b1) // Count up
            Q <= Q + 4'b0001;
        else // Count down
            Q <= Q - 4'b0001;
    end
end

endmodule

2_2/Bilgisayar Organizasyonu/Ödevler/Ödev 1/Hazır/bidirectional_counter/counter_fb_tb.v
`timescale 1ns / 1ps
`include "counter_fb.v"

module counter_fb_tb;

    // Inputs
    reg CLK, RESET, EN, DIR;
    
    // Outputs
    wire [3:0] Q;
    wire CO;
    
    counter_fb uut (
        .CLK(CLK),
        .RESET(RESET),
        .EN(EN),
        .DIR(DIR),
        .Q(Q),
        .CO(CO)
    );
    
    // Clock generation
    always #5 CLK = ~CLK;

    initial begin
        CLK = 0;
        RESET = 1;
        EN = 1;
        DIR = 1; //Count up

        $dumpfile("counter_fb_tb.vcd");
        $dumpvars(0, counter_fb_tb);
        
        #10; RESET = 0;
        
        #50;
        
        DIR = 0; //Count down
        
        #50;
        
        $finish;
    end
endmodule

//iverilog -o counter_fb_tb.vvp counter_fb_tb.v
//vvp counter_fb_tb.vvp

2_2/Bilgisayar Organizasyonu/Ödevler/Ödev 1/Hazır/bidirectional_counter/counter_fb_tb.vcd
$date
	Thu Mar 14 18:57:25 2024
$end
$version
	Icarus Verilog
$end
$timescale
	1ps
$end
$scope module counter_fb_tb $end
$var wire 4 ! Q [3:0] $end
$var wire 1 " CO $end
$var reg 1 # CLK $end
$var reg 1 $ DIR $end
$var reg 1 % EN $end
$var reg 1 & RESET $end
$scope module uut $end
$var wire 1 # CLK $end
$var wire 1 $ DIR $end
$var wire 1 % EN $end
$var wire 1 & RESET $end
$var reg 1 " CO $end
$var reg 4 ' Q [3:0] $end
$upscope $end
$upscope $end
$enddefinitions $end
$comment Show the parameter values. $end
$dumpall
$end
#0
$dumpvars
b0 '
1&
1%
1$
0#
0"
b0 !
$end
#5000
1#
#10000
0#
0&
#15000
b1 !
b1 '
1#
#20000
0#
#25000
b10 !
b10 '
1#
#30000
0#
#35000
b11 !
b11 '
1#
#40000
0#
#45000
b100 !
b100 '
1#
#50000
0#
#55000
b101 !
b101 '
1#
#60000
0#
0$
#65000
b100 !
b100 '
1#
#70000
0#
#75000
b11 !
b11 '
1#
#80000
0#
#85000
b10 !
b10 '
1#
#90000
0#
#95000
b1 !
b1 '
1#
#100000
0#
#105000
1"
b0 !
b0 '
1#
